README.txt
iCache.py
setup.py
iCache.egg-info/PKG-INFO
iCache.egg-info/SOURCES.txt
iCache.egg-info/dependency_links.txt
iCache.egg-info/top_level.txt
iCache.egg-info/zip-safe