Metadata-Version: 1.1
Name: iCache
Version: 1.0.2
Summary: A Python Cache Model
Home-page: https://github.com/15281029/PyCache
Author: Zhangbo
Author-email: 15281029@bjtu.edu.cn
License: MIT
Platform: UNKNOWN
Classifier: License :: OSI Approved :: MIT License
Classifier: Programming Language :: Python
Classifier: Intended Audience :: Developers
Classifier: Operating System :: OS Independent
